sftp_package/__init__.py
sftp_package/sftp_client.py
mytower_sftp_package-1.0.0.dist-info/LICENSE
mytower_sftp_package-1.0.0.dist-info/METADATA
mytower_sftp_package-1.0.0.dist-info/WHEEL
mytower_sftp_package-1.0.0.dist-info/top_level.txt
mytower_sftp_package-1.0.0.dist-info/RECORD
